CHANGES.txt
LICENSE.txt
MANIFEST.in
PackageInfo.cfg
README.rst
setup.cfg
setup.py
docs/pictures/bayestest-plot.png
docs/pictures/fibrillogenesis.png
docs/pictures/history-plot-trunc.png
docs/pictures/history-plot-zin-anno.png
docs/pictures/history-plot-zin.png
docs/pictures/history-plot.png
docs/pictures/norm-plot-zin-anno.png
docs/pictures/norm-plot-zin.png
docs/pictures/norm-plot.png
examples/example.cps.tmplt
examples/settings.cfg
examples/test-bayes
html/genindex.html
html/index.html
html/objects.inv
html/search.html
html/searchindex.js
html/_images/bayestest-plot.png
html/_images/fibrillogenesis.png
html/_images/history-plot-trunc.png
html/_images/history-plot-zin-anno.png
html/_images/history-plot.png
html/_images/norm-plot-zin-anno.png
html/_images/norm-plot.png
html/_sources/index.txt
html/_static/ajax-loader.gif
html/_static/basic.css
html/_static/comment-bright.png
html/_static/comment-close.png
html/_static/comment.png
html/_static/default.css
html/_static/doctools.js
html/_static/down-pressed.png
html/_static/down.png
html/_static/file.png
html/_static/jquery.js
html/_static/minus.png
html/_static/plus.png
html/_static/pygments.css
html/_static/searchtools.js
html/_static/sidebar.js
html/_static/underscore.js
html/_static/up-pressed.png
html/_static/up.png
html/_static/websupport.js
keres/__init__.py
keres/_bayestest.py
keres/_keres.py
keres/_signal.py
keres/_threader.py
keres/_version.py
keres.egg-info/PKG-INFO
keres.egg-info/SOURCES.txt
keres.egg-info/dependency_links.txt
keres.egg-info/entry_points.txt
keres.egg-info/requires.txt
keres.egg-info/top_level.txt