Metadata-Version: 1.1
Name: keres
Version: 0.8.4
Summary: A Bayes filter and test suite for amyloid fluorimetry data
Home-page: http://pypi.python.org/pypi/keres
Author: James C. Stroud
Author-email: xtald00d@gmail.com
License: BSD
Platform: UNKNOWN
Classifier: Programming Language :: Python :: 2.6
Classifier: Programming Language :: Python :: 2.7
